setup.py
Windows10/__init__.py
Windows10.egg-info/PKG-INFO
Windows10.egg-info/SOURCES.txt
Windows10.egg-info/dependency_links.txt
Windows10.egg-info/top_level.txt